{
  "_상품번호": "49466",
  "검색키워드": "미즈노윌드라이브배팅장갑,1EJEA56305,배팅장갑그레이블루,미즈노배팅글러브,야구배팅장갑,MIZUNO윌드라이브,사회인야구장갑,배팅장갑,미즈노야구장갑,윌드라이브레드",
  "SEO태그": {
    "meta_title": "미즈노 윌드라이브 레드 배팅장갑 그레이/블루 | 짱베이스볼",
    "meta_description": "미즈노(MIZUNO) 윌드라이브 레드 배팅장갑 1EJEA56305 그레이/블루. 타격 시 그립감과 내구성이 우수한 야구 배팅장갑입니다.",
    "meta_keywords": "미즈노윌드라이브배팅장갑,1EJEA56305,배팅장갑,미즈노배팅글러브,야구배팅장갑,MIZUNO윌드라이브,사회인야구장갑,야구장갑",
    "meta_author": "짱베이스볼"
  },
  "네이버EP": {
    "카테고리코드": "50001560",
    "제조사": "미즈노(MIZUNO)",
    "모델명": "1EJEA56305",
    "검색태그": "미즈노윌드라이브배팅장갑|1EJEA56305|배팅장갑|미즈노배팅글러브|야구배팅장갑|MIZUNO윌드라이브|그레이블루",
    "속성": "색상:그레이/블루|타입:배팅장갑|브랜드:MIZUNO"
  }
}
