{
  "_상품번호": "47504",
  "_상품명": "우벡스 UVEX 김도영 리미티드 에디션 스포츠 고글 선글라스 블랙/레드",
  "검색키워드": "우벡스 김도영 선글라스 블랙레드,UVEX 김도영 에디션,우벡스 스포츠 고글,김도영 선글라스,CV D5Y,리미티드 에디션 선글라스,야구 선글라스,우벡스 고글,UVEX 야구,스포츠 선글라스,야구 선수 선글라스,우벡스 리미티드,김도영 굿즈,프로 선수 선글라스,사회인야구 선글라스",
  "SEO태그": {
    "meta_title": "우벡스 김도영 리미티드 선글라스 블랙/레드 | 짱베이스볼",
    "meta_description": "우벡스 UVEX 김도영 리미티드 에디션 스포츠 고글 블랙/레드. CV D5Y 모델, 자외선 차단 렌즈, 야구 경기 전용 설계.",
    "meta_keywords": "우벡스 김도영 선글라스,UVEX 리미티드,김도영 에디션,CV D5Y,스포츠 고글,야구 선글라스,우벡스 블랙레드,자외선 차단,리미티드 에디션,야구 선수 선글라스",
    "meta_author": "짱베이스볼"
  },
  "네이버EP": {
    "카테고리코드": "50001437",
    "제조사": "우벡스(UVEX)",
    "모델명": "CV D5Y",
    "검색태그": "우벡스 김도영 선글라스|UVEX 리미티드|김도영 에디션|CV D5Y|스포츠 고글|야구 선글라스|우벡스 블랙레드|자외선 차단",
    "속성": "우벡스 스포츠 고글|CV D5Y|김도영 리미티드 에디션|블랙/레드|자외선 차단"
  }
}