{
  "_상품번호": "45835",
  "검색키워드": "모리모토 프로텍티브 2.0 경식 포수 헬멧 (무광 핑크),기타야구용품,야구보호장비,야구용품,사회인야구",
  "SEO태그": {
    "meta_title": "모리모토 프로텍티브 2.0 경식 포수 헬멧 (무광 핑크) | 짱베이스볼",
    "meta_description": "모리모토 프로텍티브 2.0 경식 포수 헬멧 (무광 핑크) 모리모토 정품. 모델: 모리모토 프로텍티브 2.0 경식 포수 헬멧. 짱베이스볼에서 만나",
    "meta_keywords": "모리모토,기타야구용품,모리모토 프로텍티브 2.0 경식 포수 헬멧",
    "meta_author": "짱베이스볼"
  },
  "네이버EP": {
    "카테고리코드": "50001437",
    "제조사": "모리모토",
    "모델명": "모리모토 프로텍티브 2.0 경식 포수 헬멧",
    "검색태그": "모리모토|기타야구용품|모리모토 프로텍티브 2.0 경식 포수 헬멧|프로텍티브|2.0|경식|포수",
    "속성": "모리모토^기타야구용품^핑크^모리모토 프로텍티브 2.0 경식 포수 헬멧"
  }
}