{
  "goodsNo": "49715",
  "seo_title": "트레이닝글러브 | 짱베이스볼",
  "seo_description": "도쿠마 수비 연습용 트레이닝 글러브 10인치 레드/탄. 작은 포켓으로 수비 기술 향상에 도움.",
  "seo_keyword": "도쿠마,트레이닝글러브,연습용글러브,수비연습글러브,10인치,레드탄,야구글러브,훈련용,야구용품,수비훈련",
  "search_keyword": "도쿠마 트레이닝 글러브,수비 연습 글러브,연습용 글러브,10인치 글러브,야구 훈련용 글러브,수비 훈련 글러브,레드탄 글러브,야구 연습 글러브,야구용품,훈련용품",
  "naver_search_tag": "도쿠마|트레이닝글러브|연습용글러브|수비연습|10인치|레드탄|야구글러브|훈련용|야구용품",
  "naver_attribute": "브랜드:도쿠마|크기:10인치|색상:레드/탄|용도:수비 연습|타입:트레이닝 글러브",
  "maker": "도쿠마",
  "meta_author": "짱베이스볼",
  "naver_category_id": "50001180"
}