{
  "goodsNo": "49322",
  "goodsNm": "뉴발란스 베이스볼 하프 집업 바람막이 NBD4EB1118 그레이",
  "metaTitle": "뉴발란스 하프집업 바람막이 | 짱베이스볼",
  "metaDescription": "뉴발란스 베이스볼 하프 집업 바람막이 NBD4EB1118 그레이. 야구 훈련과 경기에 최적화된 경량 바람막이 재킷입니다.",
  "metaKeyword": "뉴발란스 바람막이,뉴발란스 베이스볼,야구 바람막이,하프집업,NBD4EB1118,야구의류,훈련복,바람막이재킷,뉴발란스 야구복,그레이 바람막이",
  "metaAuthor": "짱베이스볼",
  "searchKeyword": "뉴발란스 바람막이, 뉴발란스 베이스볼, 야구 바람막이, 하프집업 바람막이, NBD4EB1118, 야구의류, 야구 훈련복, 바람막이 재킷, 뉴발란스 야구복, 그레이 바람막이, 야구 상의, 경량 바람막이",
  "naverSearchTag": "뉴발란스 바람막이|뉴발란스 베이스볼|야구 바람막이|하프집업|NBD4EB1118|야구의류|훈련복",
  "naverAttr": "브랜드:뉴발란스|색상:그레이|종류:바람막이",
  "maker": "뉴발란스(New Balance)",
  "naverCateCd": "50005248"
}
