{
  "_상품번호": "49397",
  "검색키워드": "미즈노프로크래프티드에디션,1AJGH33017,눗바모델글러브,경식외야글러브,미즈노프로글러브,13.2인치글러브,미즈노외야글러브,경식야구글러브,프로글러브,외야수글러브",
  "SEO태그": {
    "meta_title": "미즈노 프로 크래프티드 경식 외야글러브 눗바모델 | 짱베이스볼",
    "meta_description": "미즈노(MIZUNO) 프로 크래프티드에디션 경식 외야 글러브 13.2인치 눗바모델 1AJGH33017. 뛰어난 포구감의 프로 모델.",
    "meta_keywords": "미즈노프로크래프티드,1AJGH33017,눗바모델글러브,경식외야글러브,미즈노프로글러브,13.2인치글러브,외야글러브,경식야구글러브",
    "meta_author": "짱베이스볼"
  },
  "네이버EP": {
    "카테고리코드": "50001556",
    "제조사": "미즈노(MIZUNO)",
    "모델명": "1AJGH33017 47H",
    "검색태그": "미즈노프로크래프티드|1AJGH33017|눗바모델|경식외야글러브|미즈노프로글러브|13.2인치글러브|외야수글러브|경식야구",
    "속성": "포지션:외야|인치:13.2|대상:경식|시리즈:크래프티드에디션"
  }
}