{
  "_상품번호": "49471",
  "검색키워드": "미즈노가치수비장갑,유소년수비장갑화이트블랙,1EJEY33001,미즈노유소년장갑,야구수비장갑,미즈노Gachi,유소년야구장갑,어린이야구장갑,MIZUNO수비장갑,수비장갑",
  "SEO태그": {
    "meta_title": "미즈노 Gachi 유소년 수비장갑 화이트/블랙 | 짱베이스볼",
    "meta_description": "미즈노(MIZUNO) Gachi 유소년 수비장갑 33001/33101 화이트/블랙. 어린이 야구 선수를 위한 전문 수비장갑입니다.",
    "meta_keywords": "미즈노가치수비장갑,유소년수비장갑,1EJEY33001,미즈노유소년장갑,야구수비장갑,미즈노Gachi,유소년야구장갑,어린이야구장갑",
    "meta_author": "짱베이스볼"
  },
  "네이버EP": {
    "카테고리코드": "50001560",
    "제조사": "미즈노(MIZUNO)",
    "모델명": "1EJEY33001,1EJEY33101",
    "검색태그": "미즈노가치수비장갑|유소년수비장갑|1EJEY33001|미즈노유소년장갑|야구수비장갑|Gachi|유소년야구장갑|화이트블랙",
    "속성": "색상:화이트/블랙|대상:유소년|타입:수비장갑|브랜드:MIZUNO"
  }
}
