{
  "goodsNo": "50017",
  "seo_title": "사무라이렛가드 | 짱베이스볼",
  "seo_description": "미즈노 유소년 사무라이 렉가드 380383 블랙레드. 유소년 야구 타자용 정강이 보호대.",
  "seo_keyword": "미즈노,렉가드,유소년렉가드,사무라이렉가드,380383,블랙레드,야구보호장비,유소년야구,타자보호대,야구용품",
  "search_keyword": "미즈노 렉가드,유소년 렉가드,사무라이 렉가드,야구 렉가드,타자 보호대,유소년야구 보호장비,미즈노 유소년,380383,블랙레드 렉가드,야구용품",
  "naver_search_tag": "미즈노|렉가드|유소년렉가드|사무라이렉가드|타자보호대|야구보호장비|블랙레드|유소년야구",
  "naver_attribute": "브랜드:미즈노|대상:유소년|시리즈:사무라이|색상:블랙레드|품번:380383",
  "maker": "미즈노",
  "meta_author": "짱베이스볼",
  "naver_category_id": "50001433"
}