{
  "_상품번호": "51083",
  "검색키워드": "프랭클린글러브,아동글러브,어린이야구글러브,Franklin글러브,AIRTECH글러브,글러브볼세트,유소년글러브,입문용글러브,초등야구글러브,22880",
  "SEO태그": {
    "meta_title": "프랭클린 아동 글러브&볼 세트 | 짱베이스볼",
    "meta_description": "프랭클린 AIR TECH 8.5인치 아동용 글러브&볼 세트 22880. 야구를 처음 시작하는 어린이에게 적합한 입문용 세트입니다.",
    "meta_keywords": "프랭클린글러브,아동글러브,어린이야구글러브,Franklin,AIRTECH,글러브볼세트,유소년글러브,입문용글러브,초등야구,22880",
    "meta_author": "짱베이스볼"
  },
  "네이버EP": {
    "카테고리코드": "50001556",
    "제조사": "프랭클린(Franklin)",
    "모델명": "22880",
    "검색태그": "프랭클린글러브|아동글러브|어린이야구글러브|Franklin|AIRTECH|글러브볼세트|유소년글러브|입문용글러브",
    "속성": "사이즈:8.5인치|타입:세트상품|대상:아동"
  }
}
