{
  "_상품번호": "47505",
  "_상품명": "뉴발란스 MT410KM5 트레일 런닝화 실버",
  "검색키워드": "뉴발란스 MT410KM5,트레일 런닝화 실버,뉴발란스 트레일,야구 트레이닝화,MT410 실버,뉴발란스 운동화,트레일 슈즈,뉴발란스 야외,사회인야구 운동화,훈련화 실버,뉴발란스 KM5,스포츠 운동화,트레이닝화,뉴발란스 러닝,야구 훈련용 신발",
  "SEO태그": {
    "meta_title": "뉴발란스 MT410KM5 트레일 런닝화 실버 | 짱베이스볼",
    "meta_description": "뉴발란스 MT410KM5 트레일 런닝화 실버. 험지 주행에 강한 아웃솔, 야구 훈련 및 야외 활동 겸용.",
    "meta_keywords": "뉴발란스 MT410KM5,트레일 런닝화,뉴발란스 실버,MT410,야구 트레이닝화,트레일 슈즈,뉴발란스 운동화,훈련화,사회인야구,뉴발란스 KM5",
    "meta_author": "짱베이스볼"
  },
  "네이버EP": {
    "카테고리코드": "50001558",
    "제조사": "뉴발란스",
    "모델명": "MT410KM5",
    "검색태그": "뉴발란스 MT410KM5|트레일 런닝화|뉴발란스 실버|MT410|야구 트레이닝화|트레일 슈즈|뉴발란스 운동화|훈련화|사회인야구",
    "속성": "뉴발란스 MT410KM5|트레일 런닝화|실버|아웃도어 아웃솔|다용도 트레이닝"
  }
}