{
  "_상품번호": "40577",
  "검색키워드": "골드 GOLD GBG-PRO 068 로얄 13인치 외야 야구글러브 (나성범1)23,올라운드 글러브,야구글러브,야구용품,사회인야구",
  "SEO태그": {
    "meta_title": "골드 GOLD GBG-PRO 068 로얄 13인치 외야 야구글러브 (나성 | 짱베이스볼",
    "meta_description": "골드 GOLD GBG-PRO 068 로얄 13인치 외야 야구글러브 (나성범1)23 짱베이스볼에서 만나보세요.",
    "meta_keywords": "골드,올라운드 글러브",
    "meta_author": "짱베이스볼"
  },
  "네이버EP": {
    "카테고리코드": "50001556",
    "제조사": "골드",
    "모델명": "",
    "검색태그": "골드|올라운드 글러브|GOLD|GBG-PRO|068|로얄",
    "속성": "골드^올라운드 글러브^골드/로얄"
  }
}