{
  "_상품번호": "46708",
  "검색키워드": "나이키 드라이 핏 타이트 핏 반팔 탑 (FB7933010) 블랙,Nike,야구가방,야구용품,사회인야구",
  "SEO태그": {
    "meta_title": "나이키 드라이 핏 타이트 핏 반팔 탑 (FB7933010) 블랙 | 짱베이스볼",
    "meta_description": "나이키 드라이 핏 타이트 핏 반팔 탑 (FB7933010) 블랙 나이키 정품. 모델: FB7933010. 짱베이스볼에서 만나보세요.",
    "meta_keywords": "나이키,Nike,야구가방,FB7933010",
    "meta_author": "짱베이스볼"
  },
  "네이버EP": {
    "카테고리코드": "50001436",
    "제조사": "나이키(Nike)",
    "모델명": "FB7933010",
    "검색태그": "나이키|Nike|야구가방|FB7933010|드라이|타이트",
    "속성": "나이키^야구가방^블랙^FB7933010"
  }
}