{
  "_상품번호": "47893",
  "검색키워드": "인코자바내야글러브,코어내야글러브,11.75인치내야,CRIF43,인코자바글러브,내야수글러브,야구글러브,사회인야구,내야포지션,인코자바코어,라임그린블랙글러브,천연가죽글러브,야구용품,내야글러브,LG컬러글러브",
  "SEO태그": {
    "meta_title": "인코자바 코어 내야 글러브 11.75인치 라임/블랙 | 짱베이스볼",
    "meta_description": "인코자바 코어 내야 글러브 11.75인치 CR IF-43(LG/SB)25. 날카로운 핸들링을 지원하는 내야수 전용 글러브입니다.",
    "meta_keywords": "인코자바내야글러브,코어내야글러브,11.75인치내야,CRIF43,인코자바글러브,내야수글러브,야구글러브,사회인야구,내야포지션,인코자바",
    "meta_author": "짱베이스볼"
  },
  "네이버EP": {
    "카테고리코드": "50001556",
    "제조사": "인코자바",
    "모델명": "CR IF-43(LG/SB)25",
    "검색태그": "인코자바|코어|내야글러브|11.75인치|라임블랙|야구글러브|내야수|CRIF43",
    "속성": "포지션:내야|사이즈:11.75인치|색상:라임/블랙|브랜드:인코자바"
  }
}