{
  "_상품번호": "48303",
  "_상품명": "윌비플레이 타자 손등보호대 야구 손등가드 태극 FWB4EQPT",
  "검색키워드": "윌비플레이 손등보호대 태극,태극 손등가드,타자 손등보호대,FWB4EQPT,손등 보호대,야구 타자 보호,태극 디자인,윌비플레이 태극,핸드가드,손등 가드,야구 손보호,사회인야구 보호장비,타격 손등 보호,태극 야구용품,손등보호",
  "SEO태그": {
    "meta_title": "윌비플레이 타자 손등보호대 태극 FWB4EQPT | 짱베이스볼",
    "meta_description": "윌비플레이 태극 타자 손등보호대 FWB4EQPT. 데드볼·파울팁 충격으로부터 손등 보호. 태극 디자인 사회인야구 타자 보호장비.",
    "meta_keywords": "윌비플레이 손등보호대 태극,태극 손등가드,타자 손등보호대,FWB4EQPT,손등 보호대,야구 타자 보호,핸드가드,사회인야구 보호장비,태극 디자인,손등 가드",
    "meta_author": "짱베이스볼"
  },
  "네이버EP": {
    "카테고리코드": "50001433",
    "제조사": "윌비플레이",
    "모델명": "FWB4EQPT",
    "검색태그": "윌비플레이 손등보호대 태극|태극 손등가드|타자 손등보호대|FWB4EQPT|손등 보호대|야구 타자 보호|핸드가드|사회인야구 보호장비|태극 디자인",
    "속성": "윌비플레이|태극|손등보호대|손등가드|FWB4EQPT|타자용"
  }
}