{
  "_상품번호": "40117",
  "검색키워드": "유니 YOONI 프로 모델 외야 글러브 12.75인치 블랙/레드 YNP-003,유니컬렉터블,올라운드 글러브,야구글러브,야구용품,사회인야구",
  "SEO태그": {
    "meta_title": "유니 YOONI 프로 모델 외야 글러브 12.75인치 블랙/레드 YNP- | 짱베이스볼",
    "meta_description": "유니 YOONI 프로 모델 외야 글러브 12.75인치 블랙/레드 YNP-003 유니컬렉터블 정품. 모델: YNP-003. 짱베이스볼에서 만나보세",
    "meta_keywords": "유니컬렉터블,올라운드 글러브,YNP-003",
    "meta_author": "짱베이스볼"
  },
  "네이버EP": {
    "카테고리코드": "50001556",
    "제조사": "유니컬렉터블",
    "모델명": "YNP-003",
    "검색태그": "유니컬렉터블|올라운드 글러브|YNP-003|유니|YOONI|프로|모델|외야",
    "속성": "유니컬렉터블^올라운드 글러브^블랙/레드^YNP-003"
  }
}