{
  "_상품번호": "28503",
  "검색키워드": "Kang\\'s Studio NEW GLOVE MULTI SPONGE 글러브 스펀지,퓨전,글러브 관리용품,야구글러브,야구용품,사회인야구",
  "SEO태그": {
    "meta_title": "Kang\\'s Studio NEW GLOVE MULTI SPONGE 글러 | 짱베이스볼",
    "meta_description": "Kang\\'s Studio NEW GLOVE MULTI SPONGE 글러브 스펀지 모델: 퓨전. 짱베이스볼에서 만나보세요.",
    "meta_keywords": "Kang\\'s,글러브 관리용품,퓨전",
    "meta_author": "짱베이스볼"
  },
  "네이버EP": {
    "카테고리코드": "50001437",
    "제조사": "Kang\\'s",
    "모델명": "퓨전",
    "검색태그": "Kang\\'s|글러브 관리용품|퓨전|Studio|NEW|GLOVE|MULTI",
    "속성": "Kang\\'s^글러브 관리용품^퓨전"
  }
}