{
  "_상품번호": "47629",
  "_상품명": "다비드 프로슈트 외야 글러브",
  "검색키워드": "다비드 글러브,다비드 외야 글러브,프로슈트 글러브,외야수 글러브,DG-OF01,사회인 외야 글러브,야구 글러브 추천,외야 포지션 글러브,다비드 야구,국산 글러브",
  "SEO태그": {
    "meta_title": "다비드 프로슈트 외야 글러브 | 짱베이스볼",
    "meta_description": "다비드 프로슈트 외야수 전용 글러브. 넓은 포켓과 깊은 웹으로 플라이볼 처리에 최적화. 사회인 외야수 추천 국산 글러브.",
    "meta_keywords": "다비드 글러브,프로슈트 외야 글러브,외야수 글러브,사회인 외야 글러브,야구 글러브,DG-OF01,다비드 야구,외야 포지션,국산 글러브,야구 외야",
    "meta_author": "짱베이스볼"
  },
  "네이버EP": {
    "카테고리코드": "50001556",
    "제조사": "David",
    "모델명": "DG-OF01",
    "검색태그": "다비드 글러브|프로슈트 외야 글러브|외야수 글러브|사회인 외야 글러브|야구 글러브|다비드 야구|외야 포지션 글러브",
    "속성": "다비드 글러브|프로슈트 시리즈|외야 글러브|사회인 야구|국산 글러브|깊은 웹 포켓"
  }
}