{
  "_상품번호": "33592",
  "검색키워드": "롤링스 COOL 멀티 쿨러백 EBP10F02 (멀티 글러브가방),글러브 관리용품,야구글러브,야구용품,사회인야구",
  "SEO태그": {
    "meta_title": "롤링스 COOL 멀티 쿨러백 EBP10F02 (멀티 글러브가방) | 짱베이스볼",
    "meta_description": "롤링스 COOL 멀티 쿨러백 EBP10F02 (멀티 글러브가방) 모델: EBP10F02. 짱베이스볼에서 만나보세요.",
    "meta_keywords": "롤링스,글러브 관리용품,EBP10F02",
    "meta_author": "짱베이스볼"
  },
  "네이버EP": {
    "카테고리코드": "50001437",
    "제조사": "롤링스",
    "모델명": "EBP10F02",
    "검색태그": "롤링스|글러브 관리용품|EBP10F02|COOL|멀티|쿨러백",
    "속성": "롤링스^글러브 관리용품^EBP10F02"
  }
}